azure/synapse/spark/__init__.py
azure/synapse/spark/_configuration.py
azure/synapse/spark/_spark_client.py
azure/synapse/spark/_version.py
azure/synapse/spark/py.typed
azure/synapse/spark/aio/__init__.py
azure/synapse/spark/aio/_configuration.py
azure/synapse/spark/aio/_spark_client.py
azure/synapse/spark/aio/operations/__init__.py
azure/synapse/spark/aio/operations/_spark_batch_operations.py
azure/synapse/spark/aio/operations/_spark_session_operations.py
azure/synapse/spark/models/__init__.py
azure/synapse/spark/models/_models.py
azure/synapse/spark/models/_models_py3.py
azure/synapse/spark/models/_spark_client_enums.py
azure/synapse/spark/operations/__init__.py
azure/synapse/spark/operations/_spark_batch_operations.py
azure/synapse/spark/operations/_spark_session_operations.py
azure_synapse_spark-0.6.0.dist-info/METADATA
azure_synapse_spark-0.6.0.dist-info/WHEEL
azure_synapse_spark-0.6.0.dist-info/top_level.txt
azure_synapse_spark-0.6.0.dist-info/RECORD
