Metadata-Version: 2.1
Name: azure-synapse-spark
Version: 0.6.0
Summary: Microsoft Azure Synapse Spark Client Library for Python
Home-page: https://github.com/Azure/azure-sdk-for-python
Author: Microsoft Corporation
Author-email: azpysdkhelp@microsoft.com
License: MIT License
Platform: UNKNOWN
Classifier: Development Status :: 4 - Beta
Classifier: Programming Language :: Python
Classifier: Programming Language :: Python :: 2
Classifier: Programming Language :: Python :: 2.7
Classifier: Programming Language :: Python :: 3
Classifier: Programming Language :: Python :: 3.6
Classifier: Programming Language :: Python :: 3.7
Classifier: Programming Language :: Python :: 3.8
Classifier: Programming Language :: Python :: 3.9
Classifier: License :: OSI Approved :: MIT License
Requires-Dist: msrest (>=0.5.0)
Requires-Dist: azure-common (~=1.1)
Requires-Dist: azure-core (<2.0.0,>=1.6.0)
Requires-Dist: azure-synapse-nspkg ; python_version<'3.0'
